{
	"ingredient": { "type": "item", "code": "game:clay-fire"},
	"pattern": [[
		"##########",
		"##########",
		"##########",
		"##########",
		"##########",
		"##########",
		"##########",
		"##########",
		"##########",
	],
	[
		"##########",
		"##______##",
		"##______##",
		"##______##",
		"##______##",
		"##______##",
		"##______##",
		"###____###",
		"##########",
	],
	[
		"##########",
		"##______##",
		"##______##",
		"##______##",
		"##______##",
		"##______##",
		"##______##",
		"###____###",
		"##########",
	]],
	"name": "Helvehammerhead Mold",
	"output": { "type": "block", "code": "naturalclay:toolmold-fire-raw-helvehammer"  }
}