{
	"ingredient": { "type": "item", "code": "game:clay-fire" },
	"pattern": [[
		"#########",
		"#########",
		"#########",
		"#########",
		"#########",
		"_________",
		"_________",
		"#########",
		"#########",
		"#########",
		"#########",
		"#########",
	],
	[
		"#########",
		"#_______#",
		"#_______#",
		"#_______#",
		"#########",
		"_________",
		"_________",
		"#########",
		"#_______#",
		"#_______#",
		"#_______#",
		"#########",
	],
	[
		"#########",
		"#_______#",
		"#_______#",
		"#_______#",
		"#########",
		"_________",
		"_________",
		"#########",
		"#_______#",
		"#_______#",
		"#_______#",
		"#########",
	]],
	"name": "Ingot Mold",
	"output": { "type": "block", "code": "naturalclay:ingotmold-fire-raw", "stacksize": 2 }
}